metabot/__main__.py
metabot/botconf.py
metabot/conftest.py
metabot/datasettings.py
metabot/multibot.py
metabot/test_botconf.py
metabot/test_multibot.py
metabot/calendars/base.py
metabot/calendars/loader.py
metabot/calendars/multicalendar.py
metabot/calendars/static.py
metabot/calendars/test_base.py
metabot/calendars/test_loader.py
metabot/calendars/test_multicalendar.py
metabot/modules/admin.py
metabot/modules/countdown.py
metabot/modules/echo.py
metabot/modules/events.py
metabot/modules/groups.py
metabot/modules/help.py
metabot/modules/moderator.py
metabot/modules/natlang.py
metabot/modules/newbot.py
metabot/modules/reminders.py
metabot/modules/telegram.py
metabot/modules/test_admin.py
metabot/modules/test_countdown.py
metabot/modules/test_echo.py
metabot/modules/test_events.py
metabot/modules/test_groups.py
metabot/modules/test_help.py
metabot/modules/test_moderator.py
metabot/modules/test_natlang.py
metabot/modules/test_newbot.py
metabot/modules/test_reminders.py
metabot/modules/test_telegram.py
metabot/util/adminui.py
metabot/util/dicttools.py
metabot/util/eventutil.py
metabot/util/geoutil.py
metabot/util/html.py
metabot/util/humanize.py
metabot/util/icons.py
metabot/util/iso8601.py
metabot/util/jsonutil.py
metabot/util/modutil.py
metabot/util/msgbuilder.py
metabot/util/pickleutil.py
metabot/util/protobuf.py
metabot/util/test_adminui.py
metabot/util/test_dicttools.py
metabot/util/test_eventutil.py
metabot/util/test_html.py
metabot/util/test_humanize.py
metabot/util/test_iso8601.py
metabot/util/test_jsonutil.py
metabot/util/test_modutil.py
metabot/util/test_pickleutil.py
metabot/util/test_protobuf.py
metabot/util/test_tickets.py
metabot/util/test_yamlutil.py
metabot/util/tickets.py
metabot/util/tzutil.py
metabot/util/unicodeutil.py
metabot/util/yamlutil.py
metabot-0.3.31.dist-info/METADATA
metabot-0.3.31.dist-info/WHEEL
metabot-0.3.31.dist-info/entry_points.txt
metabot-0.3.31.dist-info/top_level.txt
metabot-0.3.31.dist-info/RECORD
