Metadata-Version: 2.4
Name: metabot
Version: 0.3.31
Summary: Modularized, multi-account bot.
Author-email: Daniel Reed <nmlorg@gmail.com>
Project-URL: Homepage, https://github.com/nmlorg/metabot
Project-URL: Issues, https://github.com/nmlorg/metabot/issues
Requires-Python: >=3.9
Requires-Dist: googlemaps
Requires-Dist: ntelebot>=0.4.5
Requires-Dist: pytz
Requires-Dist: PyYAML>=5.1
Provides-Extra: dev
Requires-Dist: pylint; extra == "dev"
Requires-Dist: pytest-cov; extra == "dev"
Requires-Dist: pytest; extra == "dev"
Requires-Dist: requests-mock; extra == "dev"
